LICENSE
LICENSE.txt
README.rst
setup.cfg
setup.py
mynameisbong/__init__.py
mynameisbong/bong.py
mynameisbong.egg-info/PKG-INFO
mynameisbong.egg-info/SOURCES.txt
mynameisbong.egg-info/dependency_links.txt
mynameisbong.egg-info/top_level.txt